dbussy.py
ravel.py
DBussy-1.2.1.dist-info/COPYING
DBussy-1.2.1.dist-info/METADATA
DBussy-1.2.1.dist-info/WHEEL
DBussy-1.2.1.dist-info/top_level.txt
DBussy-1.2.1.dist-info/RECORD
